so3krates_torch/__init__.py
so3krates_torch/blocks/embedding.py
so3krates_torch/blocks/euclidean_transformer.py
so3krates_torch/blocks/output_block.py
so3krates_torch/blocks/physical_potentials.py
so3krates_torch/blocks/radial_basis.py
so3krates_torch/blocks/so3_conv_invariants.py
so3krates_torch/calculator/so3.py
so3krates_torch/cli/jax_to_torch.py
so3krates_torch/cli/run_eval.py
so3krates_torch/cli/run_metric.py
so3krates_torch/cli/run_train.py
so3krates_torch/cli/torch_to_jax.py
so3krates_torch/data/atomic_data.py
so3krates_torch/data/neighborhood.py
so3krates_torch/data/utils.py
so3krates_torch/modules/__init__.py
so3krates_torch/modules/cutoff.py
so3krates_torch/modules/loss.py
so3krates_torch/modules/models.py
so3krates_torch/modules/spherical_harmonics.py
so3krates_torch/pretrained/so3lr/so3lr.model
so3krates_torch/scripts/simple_md.py
so3krates_torch/scripts/transform_xyz_headers.py
so3krates_torch/tests/test_model.py
so3krates_torch/tools/compile.py
so3krates_torch/tools/eval.py
so3krates_torch/tools/jax_torch_conversion.py
so3krates_torch/tools/scatter.py
so3krates_torch/tools/train.py
so3krates_torch/tools/utils.py
so3krates_torch-0.1.dist-info/licenses/LICENSE.md
so3krates_torch-0.1.dist-info/METADATA
so3krates_torch-0.1.dist-info/WHEEL
so3krates_torch-0.1.dist-info/entry_points.txt
so3krates_torch-0.1.dist-info/top_level.txt
so3krates_torch-0.1.dist-info/RECORD
