Metadata-Version: 2.4
Name: So3krates-torch
Version: 0.1
Summary: PyTorch implementation of So3krates neural network potential for atomistic simulations
Author-email: Tobias Henkes <tobias.henkes@uni.lu>
Maintainer-email: Tobias Henkes <tobias.henkes@uni.lu>
License: MIT
Project-URL: homepage, https://github.com/tohenkes/So3krates-torch
Project-URL: repository, https://github.com/tohenkes/So3krates-torch
Project-URL: documentation, https://github.com/tohenkes/So3krates-torch#readme
Project-URL: changelog, https://github.com/tohenkes/So3krates-torch/blob/main/CHANGELOG.md
Project-URL: issues, https://github.com/tohenkes/So3krates-torch/issues
Project-URL: Bug Reports, https://github.com/tohenkes/So3krates-torch/issues
Project-URL: Source Code, https://github.com/tohenkes/So3krates-torch
Keywords: machine-learning,molecular-dynamics,neural-networks,pytorch,atomistic-simulations,equivariant-networks,interatomic-potentials
Classifier: Development Status :: 3 - Alpha
Classifier: Intended Audience :: Science/Research
Classifier: License :: OSI Approved :: MIT License
Classifier: Programming Language :: Python :: 3
Classifier: Programming Language :: Python :: 3.10
Classifier: Programming Language :: Python :: 3.11
Classifier: Programming Language :: Python :: 3.12
Classifier: Topic :: Scientific/Engineering :: Chemistry
Classifier: Topic :: Scientific/Engineering :: Physics
Classifier: Topic :: Scientific/Engineering :: Artificial Intelligence
Classifier: Operating System :: POSIX :: Linux
Classifier: Environment :: GPU :: NVIDIA CUDA
Requires-Python: >=3.10
License-File: LICENSE.md
Requires-Dist: ase>=3.26.0
Requires-Dist: h5py>=3.14.0
Requires-Dist: mace-torch>=0.3.14
Requires-Dist: numpy>=1.26.4
Requires-Dist: pyyaml>=6.0.2
Requires-Dist: torch>=2.8.0
Requires-Dist: torchvision>=0.23.0
Requires-Dist: torchaudio>=2.8.0
Provides-Extra: dev
Requires-Dist: pre-commit; extra == "dev"
Requires-Dist: pytest; extra == "dev"
Dynamic: license-file
